fw2ai.py
list/__init__.py
list/commands.py
main/__init__.py
main/commands.py
fw2ai-0.1.1.dist-info/METADATA
fw2ai-0.1.1.dist-info/WHEEL
fw2ai-0.1.1.dist-info/entry_points.txt
fw2ai-0.1.1.dist-info/top_level.txt
fw2ai-0.1.1.dist-info/RECORD
