Metadata-Version: 2.1
Name: fw2ai
Version: 0.1.1
Summary: Making security analysis simpler by applying AI to binary artefacts of firmware
Home-page: https://github.com/cpuinfo/fw2ai.git
Author: Mahesh Patil
Author-email: cpuinfo10@gmail.com
License: UNKNOWN
Platform: UNKNOWN
Classifier: Programming Language :: Python :: 3
Classifier: License :: OSI Approved :: MIT License
Classifier: Operating System :: OS Independent
Requires-Python: >=3.6
Requires-Dist: Click
